finVizFetchPkg/__init__.py
finVizFetchPkg/finVizScaper.py
finVizFetchPkg-0.0.2.dist-info/METADATA
finVizFetchPkg-0.0.2.dist-info/WHEEL
finVizFetchPkg-0.0.2.dist-info/top_level.txt
finVizFetchPkg-0.0.2.dist-info/RECORD
